[
    {
        "id": 1,
        "name": "DigiSoul",
        "desc": "Temos banners e claro tudo ao melhor preço",
        "price": 6600
    },
    {
        "id": 2,
        "name": "Yendza",
        "desc": "Temos banners de diferentes tipos e qualidade e co melhor preço",
        "price": 5200
    },
    {
        "id": 3,
        "name": "Riha",
        "desc": "Lorem ipsum dolor sit amet consectetur adipisicing elit. Et soluta atque voluptatum deleniti veritatis laborum natus odio, tempora suscipit ullam totam omnis possimus eos iste?",
        "price": 1700
    },
    {
        "id": 4,
        "name": "Muyendzi",
        "desc": "Lorem ipsum dolor sit amet, consectetur adipisicing elit. Rerum cumque fugit modi. Vel, in cupiditate magni voluptatibus tempore sed provident odit, mollitia ratione fuga cum deleniti, ipsum voluptates pariatur similique?",
        "price": 2400
    },
    {
        "id": 5,
        "name": "Nhonguista Organizado",
        "desc": "Lorem ipsum dolor sit amet consectetur, adipisicing elit. Expedita possimus, veniam aspernatur quis soluta optio illum placeat.",
        "price": 3300
    },
    {
        "id": 6,
        "name": "Bakito Inc",
        "desc": "Lorem ipsum dolor sit amet consectetur adipisicing elit. Cupiditate, voluptatem?",
        "price": 10000
    },
    {
        "id": 7,
        "name": "Rutty SMS",
        "desc": "Lorem ipsum, dolor sit amet consectetur adipisicing elit. Dolor deleniti sequi, cupiditate est dolores minima quasi assumenda nulla rem vitae ad alias numquam sint et veniam optio quos perspiciatis sunt nisi delectus?",
        "price": 3400
    },
    {
        "id": 8,
        "name": "wizzo",
        "desc": "Técnica de impressão versátil, ideal para materiais rígidos e flexíveis, oferecendo cores vibrantes e durabilidade.",
        "price": 2100
    },
    {
        "id": 9,
        "name": "XIMUSSI",
        "desc": "Lorem, ipsum dolor sit amet consectetur adipisicing elit. Dolorem aliquid dicta ea voluptas voluptate iusto.",
        "price": 5900
    }
]